chartic/__init__.py
chartic/chartic.py
chartic-0.0.1.dist-info/LICENSE
chartic-0.0.1.dist-info/METADATA
chartic-0.0.1.dist-info/WHEEL
chartic-0.0.1.dist-info/top_level.txt
chartic-0.0.1.dist-info/RECORD
