Metadata-Version: 2.1
Name: chartic
Version: 0.0.1
Summary: Chartic API
Author-email: Pedram Parsian <pedram.parsian@gmail.com>
License: MIT License
Project-URL: Homepage, https://github.com/chartic-ir/chartic
Keywords: chartic,api
Classifier: License :: OSI Approved :: MIT License
Classifier: Programming Language :: Python
Classifier: Programming Language :: Python :: 3
Requires-Python: >=3.10
License-File: LICENSE
